{
    "links": {
        "self": "https://browsercompat.org/api/v2/sections/8"
    },
    "data": {
        "type": "sections",
        "id": "8",
        "attributes": {
            "number": {
                "en": "2.1"
            },
            "name": {
                "en": "Ruby-specific 'display' Values"
            },
            "subpath": {
                "en": "#ruby-display"
            }
        },
        "relationships": {
            "references": {
                "links": {
                    "self": "https://browsercompat.org/api/v2/sections/8/relationships/references",
                    "related": "https://browsercompat.org/api/v2/sections/8/references"
                },
                "data": []
            },
            "specification": {
                "links": {
                    "self": "https://browsercompat.org/api/v2/sections/8/relationships/specification",
                    "related": "https://browsercompat.org/api/v2/sections/8/specification"
                },
                "data": {
                    "type": "specifications",
                    "id": "4"
                }
            },
            "history_current": {
                "links": {
                    "self": "https://browsercompat.org/api/v2/sections/8/relationships/history_current",
                    "related": "https://browsercompat.org/api/v2/sections/8/history_current"
                },
                "data": {
                    "type": "historical_sections",
                    "id": "9"
                }
            },
            "history": {
                "links": {
                    "self": "https://browsercompat.org/api/v2/sections/8/relationships/history",
                    "related": "https://browsercompat.org/api/v2/sections/8/history"
                },
                "data": [
                    {
                        "type": "historical_sections",
                        "id": "9"
                    },
                    {
                        "type": "historical_sections",
                        "id": "8"
                    }
                ]
            }
        }
    }
}
