{
    "historical_specifications": [
        {
            "id": "1",
            "date": "2015-04-20T18:57:10.470658Z",
            "event": "created",
            "specifications": {
                "id": "1",
                "slug": "css1",
                "mdn_key": "CSS1",
                "name": {
                    "en": "CSS Level&nbsp;1"
                },
                "uri": {
                    "en": "http://www.w3.org/TR/CSS1/"
                },
                "links": {
                    "maturity": "1",
                    "sections": [],
                    "history_current": "1"
                }
            },
            "links": {
                "changeset": "1",
                "specification": "1"
            }
        }
    ],
    "links": {
        "historical_specifications.changeset": {
            "type": "changesets",
            "href": "https://browsercompat.org/api/v1/changesets/{historical_specifications.changeset}"
        },
        "historical_specifications.specification": {
            "type": "specifications",
            "href": "https://browsercompat.org/api/v1/specifications/{historical_specifications.specification}"
        }
    },
    "meta": {
        "pagination": {
            "historical_specifications": {
                "previous": null,
                "next": null,
                "count": 1
            }
        }
    }
}
